re_transliterate.py
re_transliterate-1.3.dist-info/DESCRIPTION.rst
re_transliterate-1.3.dist-info/METADATA
re_transliterate-1.3.dist-info/pydist.json
re_transliterate-1.3.dist-info/RECORD
re_transliterate-1.3.dist-info/top_level.txt
re_transliterate-1.3.dist-info/WHEEL
