Metadata-Version: 2.0
Name: re-transliterate
Version: 1.3
Summary: Functions for transliteration using regular expressions
Home-page: https://github.com/MatthewDarling/re_transliterate/
Author: Matthew Darling
Author-email: matthewjdarling@gmail.com
License: http://opensource.org/licenses/MIT
Platform: UNKNOWN
Classifier: Development Status :: 5 - Production/Stable
Classifier: Intended Audience :: Science/Research
Classifier: License :: OSI Approved :: MIT License
Classifier: Natural Language :: English
Classifier: Operating System :: OS Independent
Classifier: Programming Language :: Python
Classifier: Programming Language :: Python :: 2
Classifier: Programming Language :: Python :: 3
Classifier: Topic :: Scientific/Engineering
